desktop_entry_creator/__init__.py
desktop_entry_creator/app.py
desktop_entry_creator/res/alert.png
desktop_entry_creator/res/error.png
desktop_entry_creator/res/icon.png
desktop_entry_creator/res/icon.svg
desktop_entry_creator/res/success.png
desktop_entry_creator/res/ui.glade
desktop_entry_creator/res/ui.glade~
desktop_entry_creator-0.1.4.dist-info/METADATA
desktop_entry_creator-0.1.4.dist-info/RECORD
desktop_entry_creator-0.1.4.dist-info/WHEEL
desktop_entry_creator-0.1.4.dist-info/entry_points.txt
desktop_entry_creator-0.1.4.dist-info/top_level.txt
