Metadata-Version: 2.1
Name: desktop-entry-creator
Version: 0.1.4
Summary: A user-friendly GUI for creating desktop entries for installed applications on Linux.
Home-page: https://github.com/faheel/desktop-entry-creator
Author: Faheel Ahmad
Author-email: faheel@live.in
License: GPLv3
Project-URL: Bug Reports, https://github.com/faheel/desktop-entry-creator/issues
Project-URL: Source, https://github.com/faheel/desktop-entry-creator
Keywords: gui linux desktop-entry desktop-entry-creator pygobject gtk
Platform: UNKNOWN
Classifier: Natural Language :: English
Classifier: Development Status :: 4 - Beta
Classifier: Operating System :: POSIX :: Linux
Classifier: Programming Language :: Python :: 3
Classifier: Programming Language :: Python :: 3.4
Classifier: Programming Language :: Python :: 3.5
Classifier: Programming Language :: Python :: 3.6
Classifier: Programming Language :: Python :: 3.7
Classifier: License :: OSI Approved :: GNU General Public License v3 (GPLv3)
Classifier: Topic :: Utilities
Classifier: Environment :: X11 Applications
Classifier: Intended Audience :: End Users/Desktop
Provides-Extra: dev
Requires-Dist: pygobject
Requires-Dist: python-slugify
Provides-Extra: dev
Requires-Dist: pylint; extra == 'dev'
